example_package_wangxwei/__init__.py
example_package_wangxwei/example.py
example_package_wangxwei-0.0.2.dist-info/METADATA
example_package_wangxwei-0.0.2.dist-info/WHEEL
example_package_wangxwei-0.0.2.dist-info/licenses/LICENSE
example_package_wangxwei-0.0.2.dist-info/RECORD
