Metadata-Version: 2.1
Name: example_package_wangxwei
Version: 0.0.2
Summary: A small example package for using PyPI repository
Project-URL: Homepage, https://github.com/WriteWhatLearned/WriteWhatLearned.github.io
Project-URL: Bug Tracker, https://github.com/WriteWhatLearned/WriteWhatLearned.github.io/issues
Author-email: wangxwei <writewhatlearned@foxmail.com>
License-File: LICENSE
Classifier: License :: OSI Approved :: MIT License
Classifier: Natural Language :: Chinese (Simplified)
Classifier: Operating System :: OS Independent
Classifier: Programming Language :: Python :: 3 :: Only
Requires-Python: >=3.7
